eas_3d_pattern/__init__.py
eas_3d_pattern/parser.py
eas_3d_pattern/sample_data/__init__.py
eas_3d_pattern/sample_data/VENDOR_ANTMODEL1_2100_A-Y1_RFp01_T00p0_P45_NonUniformSampling_3drp.json
eas_3d_pattern/sample_data/VENDOR_ANTMODEL2_2100_A-Y1_RFp01_T00p0_P45_UniformSampling_3drp.json
eas_3d_pattern/sample_data/VENDOR_ANTMODEL3_3700_EID12345_T00p0_P45_NonUniformSampling_3drp.json
eas_3d_pattern/sample_data/VENDOR_ANTMODEL4_3700_BID67890_T00p0_P45_UniformSampling_3drp.json
eas_3d_pattern/schema_manager.py
eas_3d_pattern/schemas/__init__.py
eas_3d_pattern/schemas/NGMN_BASTA_AA_3drp_JSON_Schema_WP3_0_latest.json
eas_3d_pattern/sector_definitions.py
eas_3d_pattern/util_func/__init__.py
eas_3d_pattern/util_func/report.py
eas_3d_pattern-0.1.3.dist-info/licenses/LICENSE
eas_3d_pattern-0.1.3.dist-info/METADATA
eas_3d_pattern-0.1.3.dist-info/WHEEL
eas_3d_pattern-0.1.3.dist-info/RECORD
