Metadata-Version: 2.4
Name: eas-3d-pattern
Version: 0.1.3
Summary: A tool to visualize 3D antenna pattern files in JSON format.
License: MIT License
License-File: LICENSE
Keywords: antenna,pattern,3d pattern,visualization,NGMN,BASTA,RF,JSON
Author: Georg Polownikow
Author-email: georg.polownikow@gmail.com
Requires-Python: >=3.11,<3.14
Classifier: Development Status :: 3 - Alpha
Classifier: Intended Audience :: Telecommunications Industry
Classifier: Intended Audience :: Science/Research
Classifier: License :: OSI Approved :: MIT License
Classifier: Programming Language :: Python :: 3
Classifier: Programming Language :: Python :: 3.11
Classifier: Programming Language :: Python :: 3.12
Classifier: Programming Language :: Python :: 3.13
Classifier: Operating System :: OS Independent
Classifier: Topic :: Scientific/Engineering :: Visualization
Requires-Dist: jsonschema (>=4.24.0,<5.0.0)
Requires-Dist: kaleido (>=0.1.0,<0.2.0)
Requires-Dist: nbformat (>=4.2.0,<6.0.0)
Requires-Dist: numpy (>=2.0.0,<3.0.0)
Requires-Dist: openpyxl (>=3.1.5,<4.0.0)
Requires-Dist: pandas (>=2.2.2,<3.0.0)
Requires-Dist: plotly (>=5.24.1,<6.0.0)
Requires-Dist: requests (>=2.32.2,<3.0.0)
Requires-Dist: tqdm (>=4.67.1,<5.0.0)
Requires-Dist: xarray (>=2025.3.1,<2026.0.0)
Project-URL: Homepage, https://www.ericsson.com/antenna-system
Project-URL: Repository, https://github.com/Ericsson/eas-3d-pattern
